[
  {
    "titre": "Aspirant",
    "art": "L'",
    "titreVo": "",
    "idFilm": 143758,
    "ageMinimal": null,
    "realisateurs": "Souleymane Cissé",
    "annee": 1968,
    "pays": "Mali",
    "textes": [
      {
        "typeTexte": 9,
        "texte": "XXX"
      }
    ]
  },
  {
    "titre": "Aux pays Dogon",
    "titreVo": "",
    "idFilm": 144075,
    "ageMinimal": null,
    "realisateurs": "Souleymane Cissé",
    "annee": 2006,
    "pays": "Mali",
    "textes": [
      {
        "typeTexte": 9,
        "texte": "XX"
      }
    ]
  },
  {
    "titre": "Chanteurs traditionnels des îles Seychelles",
    "art": "Les",
    "titreVo": "",
    "idFilm": 143734,
    "ageMinimal": null,
    "realisateurs": "Souleymane Cissé",
    "annee": 1978,
    "pays": "Mali",
    "textes": [
      {
        "typeTexte": 9,
        "texte": "Les conteurs et musiciens traditionnels seychellois expriment leur inquiétude face au modernisme et au désintérêt des jeunes pour la musique traditionnelle."
      }
    ]
  },
  {
    "titre": "Cinq jours d'une vie",
    "titreVo": "",
    "idFilm": 143736,
    "ageMinimal": null,
    "realisateurs": "Souleymane Cissé",
    "annee": 1972,
    "pays": "Mali-Sénégal",
    "textes": [
      {
        "typeTexte": 9,
        "texte": "XX"
      }
    ]
  },
  {
    "titre": "Degal à Dialloubé",
    "titreVo": "",
    "idFilm": 143759,
    "ageMinimal": null,
    "realisateurs": "Souleymane Cissé",
    "annee": 1970,
    "pays": "Mali",
    "textes": [
      {
        "typeTexte": 9,
        "texte": "XXXX"
      }
    ]
  },
  {
    "titre": "Devin de N'golonina",
    "art": "Le",
    "titreVo": "",
    "idFilm": 144074,
    "ageMinimal": null,
    "realisateurs": "Souleymane Cissé",
    "annee": 1998,
    "pays": "Mali",
    "textes": [
      {
        "typeTexte": 9,
        "texte": "XXX"
      }
    ]
  },
  {
    "titre": "Dis moi qui tu es",
    "titreVo": "Min ye",
    "idFilm": 108314,
    "ageMinimal": null,
    "realisateurs": "Souleymane Cissé",
    "annee": 2008,
    "pays": "Mali-France",
    "textes": [
      {
        "typeTexte": 9,
        "texte": "Au sein d'un couple de la bourgeoisie bamakoise, Issa décide d'épouser une seconde femme. Lassée de la polygamie et de la routine du mariage, Mimi prend à son tour un amant. Leurs difficultés surpassent pourtant ce quotidien à trois."
      }
    ],
    "generique": [
      "Sokona Gakou",
      "Assane Kouyaté",
      "Badra Alou Sissoko"
    ]
  },
  {
    "titre": "Dixième anniversaire de l'Organisation de l'Unité Africaine",
    "titreVo": "",
    "idFilm": 143763,
    "ageMinimal": null,
    "realisateurs": "Souleymane Cissé",
    "annee": 1973,
    "pays": "Mali",
    "textes": [
      {
        "typeTexte": 9,
        "texte": "XXX"
      }
    ]
  },
  {
    "titre": "Fête du Sanké",
    "titreVo": "",
    "idFilm": 143760,
    "ageMinimal": null,
    "realisateurs": "Souleymane Cissé",
    "annee": 1971,
    "pays": "Mali",
    "textes": [
      {
        "typeTexte": 9,
        "texte": "XXX"
      }
    ]
  },
  {
    "titre": "Homme et les idoles = L'Homme et ses idoles",
    "art": "L'",
    "titreVo": "",
    "idFilm": 143762,
    "ageMinimal": null,
    "realisateurs": "Souleymane Cissé",
    "annee": 1965,
    "pays": "Mali",
    "textes": [
      {
        "typeTexte": 9,
        "texte": "XXX"
      }
    ]
  },
  {
    "titre": "Jeune fille",
    "art": "La",
    "titreVo": "Den muso",
    "idFilm": 63766,
    "ageMinimal": null,
    "realisateurs": "Souleymane Cissé",
    "annee": 1975,
    "pays": "Mali",
    "textes": [
      {
        "typeTexte": 9,
        "texte": "Une jeune femme muette est violée et tombe enceinte. Ce drame a des conséquences désastreuses pour elle et sa famille."
      }
    ],
    "generique": [
      "Dounamba Dany Coulibaly",
      "Balla Moussa Keïta",
      "Oumou Diarra"
    ]
  },
  {
    "titre": "Lumière",
    "art": "La",
    "titreVo": "Yeelen",
    "idFilm": 38127,
    "ageMinimal": null,
    "realisateurs": "Souleymane Cissé",
    "annee": 1987,
    "pays": "Mali",
    "textes": [
      {
        "typeTexte": 9,
        "texte": "Un jeune homme doté de pouvoirs magiques demande de l'aide à son oncle pour combattre son père sorcier."
      }
    ],
    "generique": [
      "Issiaka Kane",
      "Balla Moussa Keïta",
      "Aoua Sangaré"
    ]
  },
  {
    "titre": "Martin Scorsese au Mali",
    "titreVo": "",
    "idFilm": 144076,
    "ageMinimal": null,
    "realisateurs": "Souleymane Cissé",
    "annee": 2007,
    "pays": "Mali",
    "textes": [
      {
        "typeTexte": 9,
        "texte": "Journal filmé du séjour de Martin Scorsese à Bamako à l'invitation de Souleymane Cissé pour prendre part à des discussions sur la création cinématographique malienne et la sauvegarde de son patrimoine."
      }
    ]
  },
  {
    "titre": "Nye (l'œil du cyclone)",
    "titreVo": "",
    "idFilm": 144079,
    "ageMinimal": null,
    "realisateurs": "Souleymane Cissé",
    "annee": 2005,
    "pays": "Mali",
    "textes": [
      {
        "typeTexte": 9,
        "texte": "XXXX"
      }
    ]
  },
  {
    "titre": "O ka",
    "titreVo": "",
    "idFilm": 127006,
    "ageMinimal": null,
    "realisateurs": "Souleymane Cissé",
    "annee": 2014,
    "pays": "Mali",
    "textes": [
      {
        "typeTexte": 9,
        "texte": "Alors que ses sœurs sont expulsées de la maison de famille, Souleymane Cissé revient sur ses souvenirs d'enfance, son histoire, sa ville de Bamako et l'état géopolitique actuel du Mali."
      }
    ]
  },
  {
    "titre": "O. Sembène",
    "titreVo": "",
    "idFilm": 144066,
    "ageMinimal": null,
    "realisateurs": "Souleymane Cissé",
    "annee": 2007,
    "pays": "Mali-Sénégal",
    "textes": [
      {
        "typeTexte": 9,
        "texte": "Portrait du père du cinéma sénégalais Ousmane Sembène par Souleymane Cissé avec, comme lien entre les deux artistes, la musique de Youssou N'Dour."
      }
    ]
  },
  {
    "titre": "Sory",
    "titreVo": "",
    "idFilm": 144077,
    "ageMinimal": null,
    "realisateurs": "Souleymane Cissé",
    "annee": 2002,
    "pays": "Mali",
    "textes": [
      {
        "typeTexte": 9,
        "texte": "XXXX"
      }
    ]
  },
  {
    "titre": "Souleymane Cissé",
    "titreVo": "",
    "idFilm": 61740,
    "ageMinimal": 0,
    "realisateurs": "Rithy Panh",
    "annee": 1991,
    "pays": "France",
    "textes": [
      {
        "typeTexte": 9,
        "texte": "Face à la caméra de Rithy Panh, Souleymane Cissé livre sa vision du cinéma, de l'Afrique et du monde."
      }
    ]
  },
  {
    "titre": "Sources d'inspiration",
    "titreVo": "",
    "idFilm": 143735,
    "ageMinimal": null,
    "realisateurs": "Souleymane Cissé",
    "annee": 1968,
    "pays": "Mali",
    "textes": [
      {
        "typeTexte": 9,
        "texte": "XXX"
      }
    ]
  },
  {
    "titre": "Travail",
    "art": "Le",
    "titreVo": "Baara",
    "idFilm": 62082,
    "ageMinimal": 0,
    "realisateurs": "Souleymane Cissé",
    "annee": 1978,
    "pays": "Mali",
    "textes": [
      {
        "typeTexte": 9,
        "texte": "Les destinées parallèles de deux amis, prénommés tous deux Balla. L'un est ingénieur, l'autre petit vendeur des rues."
      }
    ],
    "generique": [
      "Oumou Diarra",
      "Boubacar Keïta",
      "Baba Niaré"
    ]
  },
  {
    "titre": "Vent",
    "art": "Le",
    "titreVo": "Finyè",
    "idFilm": 54808,
    "ageMinimal": null,
    "realisateurs": "Souleymane Cissé",
    "annee": 1982,
    "pays": "Mali",
    "textes": [
      {
        "typeTexte": 9,
        "texte": "Au cours de manifestations, Bah et Batrou, deux étudiants refusant l'ordre établi, sont arrêtés. Ils découvrent l'emprisonnement, la souffrance physique, l'humiliation. Une épreuve qui, loin de les affaiblir, les rapproche et leur donne la force de résister."
      }
    ],
    "generique": [
      "Fousseyni Sissoko",
      "Goundo Guissé",
      "Balla Moussa Keïta"
    ]
  },
  {
    "titre": "Waati – Le temps",
    "titreVo": "",
    "idFilm": 53761,
    "ageMinimal": null,
    "realisateurs": "Souleymane Cissé",
    "annee": 1994,
    "pays": "France-Mali",
    "textes": [
      {
        "typeTexte": 9,
        "texte": "En Afrique du Sud, Nandi subit l'humiliation et l'injustice de l'Apartheid. Lorsque son père est brutalement assassiné par un policier blanc, elle se venge en l'abattant à son tour. Elle s'enfuit alors vers l'ouest dans l'espoir d'une vie meilleure."
      }
    ]
  },
  {
    "titre": "Yahooo (Chants des Massaï)",
    "titreVo": "",
    "idFilm": 144078,
    "ageMinimal": null,
    "realisateurs": "Souleymane Cissé",
    "annee": 1998,
    "pays": "Mali",
    "textes": [
      {
        "typeTexte": 9,
        "texte": "XXXX"
      }
    ]
  }
]